tests/__init__.py
tests/test_collection.py
zhaogang_collection/__init__.py
zhaogang_collection/main.py
zhaogang_collection-0.0.1.dist-info/METADATA
zhaogang_collection-0.0.1.dist-info/WHEEL
zhaogang_collection-0.0.1.dist-info/top_level.txt
zhaogang_collection-0.0.1.dist-info/RECORD
